{
  "$schema": "https://raw.githubusercontent.com/spdx/spdx-spec/v2.2.1/schemas/spdx-schema.json",
  "spdxVersion": "SPDX-2.2",
  "dataLicense": "CC0-1.0",
  "SPDXID": "SPDXRef-DOCUMENT",
  "documentNamespace": "https://spdx.org/spdxdocs/glew-x64-linux-2.3.1-b6f4966b-01ea-4c85-9183-3a4b0e9b29a6",
  "name": "glew:x64-linux@2.3.1 dd582aba0131f6edb131a7b1d96ed44a16cb7b2e0e3920853e1b46f1c5ee6a9c",
  "creationInfo": {
    "creators": [
      "Tool: vcpkg-2026-04-08-e0612b42ce44e55a0e630f2ee9d3c533a63d8bc1"
    ],
    "created": "2026-05-06T11:49:26Z"
  },
  "relationships": [
    {
      "spdxElementId": "SPDXRef-port",
      "relationshipType": "GENERATES",
      "relatedSpdxElement": "SPDXRef-binary"
    },
    {
      "spdxElementId": "SPDXRef-port",
      "relationshipType": "CONTAINS",
      "relatedSpdxElement": "SPDXRef-port-file-0"
    },
    {
      "spdxElementId": "SPDXRef-port",
      "relationshipType": "CONTAINS",
      "relatedSpdxElement": "SPDXRef-port-file-1"
    },
    {
      "spdxElementId": "SPDXRef-port",
      "relationshipType": "CONTAINS",
      "relatedSpdxElement": "SPDXRef-port-file-2"
    },
    {
      "spdxElementId": "SPDXRef-port",
      "relationshipType": "CONTAINS",
      "relatedSpdxElement": "SPDXRef-port-file-3"
    },
    {
      "spdxElementId": "SPDXRef-port",
      "relationshipType": "CONTAINS",
      "relatedSpdxElement": "SPDXRef-port-file-4"
    },
    {
      "spdxElementId": "SPDXRef-port",
      "relationshipType": "CONTAINS",
      "relatedSpdxElement": "SPDXRef-port-file-5"
    },
    {
      "spdxElementId": "SPDXRef-port-file-5",
      "relationshipType": "DEPENDENCY_MANIFEST_OF",
      "relatedSpdxElement": "SPDXRef-port"
    },
    {
      "spdxElementId": "SPDXRef-binary",
      "relationshipType": "CONTAINS",
      "relatedSpdxElement": "SPDXRef-binary-file-0"
    },
    {
      "spdxElementId": "SPDXRef-binary",
      "relationshipType": "CONTAINS",
      "relatedSpdxElement": "SPDXRef-binary-file-1"
    },
    {
      "spdxElementId": "SPDXRef-binary",
      "relationshipType": "CONTAINS",
      "relatedSpdxElement": "SPDXRef-binary-file-2"
    },
    {
      "spdxElementId": "SPDXRef-binary",
      "relationshipType": "CONTAINS",
      "relatedSpdxElement": "SPDXRef-binary-file-3"
    },
    {
      "spdxElementId": "SPDXRef-binary",
      "relationshipType": "CONTAINS",
      "relatedSpdxElement": "SPDXRef-binary-file-4"
    },
    {
      "spdxElementId": "SPDXRef-binary",
      "relationshipType": "CONTAINS",
      "relatedSpdxElement": "SPDXRef-binary-file-5"
    },
    {
      "spdxElementId": "SPDXRef-binary",
      "relationshipType": "CONTAINS",
      "relatedSpdxElement": "SPDXRef-binary-file-6"
    },
    {
      "spdxElementId": "SPDXRef-binary",
      "relationshipType": "CONTAINS",
      "relatedSpdxElement": "SPDXRef-binary-file-7"
    },
    {
      "spdxElementId": "SPDXRef-binary",
      "relationshipType": "CONTAINS",
      "relatedSpdxElement": "SPDXRef-binary-file-8"
    },
    {
      "spdxElementId": "SPDXRef-binary",
      "relationshipType": "CONTAINS",
      "relatedSpdxElement": "SPDXRef-binary-file-9"
    },
    {
      "spdxElementId": "SPDXRef-binary",
      "relationshipType": "CONTAINS",
      "relatedSpdxElement": "SPDXRef-binary-file-10"
    },
    {
      "spdxElementId": "SPDXRef-binary",
      "relationshipType": "CONTAINS",
      "relatedSpdxElement": "SPDXRef-binary-file-11"
    },
    {
      "spdxElementId": "SPDXRef-binary",
      "relationshipType": "CONTAINS",
      "relatedSpdxElement": "SPDXRef-binary-file-12"
    },
    {
      "spdxElementId": "SPDXRef-binary",
      "relationshipType": "CONTAINS",
      "relatedSpdxElement": "SPDXRef-binary-file-13"
    },
    {
      "spdxElementId": "SPDXRef-binary",
      "relationshipType": "CONTAINS",
      "relatedSpdxElement": "SPDXRef-binary-file-14"
    },
    {
      "spdxElementId": "SPDXRef-binary",
      "relationshipType": "CONTAINS",
      "relatedSpdxElement": "SPDXRef-binary-file-15"
    },
    {
      "spdxElementId": "SPDXRef-binary",
      "relationshipType": "CONTAINS",
      "relatedSpdxElement": "SPDXRef-binary-file-16"
    }
  ],
  "packages": [
    {
      "name": "glew",
      "SPDXID": "SPDXRef-port",
      "versionInfo": "2.3.1",
      "downloadLocation": "git+https://github.com/Microsoft/vcpkg#ports/glew",
      "homepage": "https://github.com/nigels-com/glew",
      "licenseConcluded": "NOASSERTION",
      "licenseDeclared": "NOASSERTION",
      "copyrightText": "NOASSERTION",
      "description": "The OpenGL Extension Wrangler Library (GLEW) is a cross-platform open-source C/C++ extension loading library.",
      "comment": "This is the port (recipe) consumed by vcpkg."
    },
    {
      "name": "glew:x64-linux",
      "SPDXID": "SPDXRef-binary",
      "versionInfo": "dd582aba0131f6edb131a7b1d96ed44a16cb7b2e0e3920853e1b46f1c5ee6a9c",
      "downloadLocation": "NONE",
      "licenseConcluded": "NOASSERTION",
      "licenseDeclared": "NOASSERTION",
      "copyrightText": "NOASSERTION",
      "comment": "This is a binary package built by vcpkg."
    },
    {
      "SPDXID": "SPDXRef-resource-0",
      "name": "glew-2.3.1.tgz",
      "packageFileName": "glew-2.3.1.tgz",
      "downloadLocation": "https://github.com/nigels-com/glew/releases/download/glew-2.3.1/glew-2.3.1.tgz",
      "licenseConcluded": "NOASSERTION",
      "licenseDeclared": "NOASSERTION",
      "copyrightText": "NOASSERTION",
      "checksums": [
        {
          "algorithm": "SHA512",
          "checksumValue": "cb4caecf32ec0f180c2691dc7769ffc99571c64f259a2663a2b80e788f1c2fd5362c59e0caaeefed6fb78a4070366d244666a657358049b09071b59fae2377e0"
        }
      ]
    }
  ],
  "files": [
    {
      "fileName": "./trim-build.diff",
      "SPDXID": "SPDXRef-port-file-0",
      "checksums": [
        {
          "algorithm": "SHA256",
          "checksumValue": "3dbda642b70f41104b5304b73f00c824104a0c783db940e20dc38f7a3c06196b"
        }
      ],
      "licenseConcluded": "NOASSERTION",
      "copyrightText": "NOASSERTION"
    },
    {
      "fileName": "./portfile.cmake",
      "SPDXID": "SPDXRef-port-file-1",
      "checksums": [
        {
          "algorithm": "SHA256",
          "checksumValue": "f28493fa0a80f7f73effa141030239146d635ef4bf7ac45377256f38ee9e11e2"
        }
      ],
      "licenseConcluded": "NOASSERTION",
      "copyrightText": "NOASSERTION"
    },
    {
      "fileName": "./fix-LNK2019.patch",
      "SPDXID": "SPDXRef-port-file-2",
      "checksums": [
        {
          "algorithm": "SHA256",
          "checksumValue": "d43b152fa36e1db492573c0b0b7e1ea7b59cf1b81d59ea16cf4c25b2de5eae06"
        }
      ],
      "licenseConcluded": "NOASSERTION",
      "copyrightText": "NOASSERTION"
    },
    {
      "fileName": "./vcpkg-cmake-wrapper.cmake",
      "SPDXID": "SPDXRef-port-file-3",
      "checksums": [
        {
          "algorithm": "SHA256",
          "checksumValue": "8a5f7ae6b0f3ddac45595a1edeb4f3c0d1a612280eaf2d029904e99b6c03816c"
        }
      ],
      "licenseConcluded": "NOASSERTION",
      "copyrightText": "NOASSERTION"
    },
    {
      "fileName": "./usage",
      "SPDXID": "SPDXRef-port-file-4",
      "checksums": [
        {
          "algorithm": "SHA256",
          "checksumValue": "32953fbc39053f27a0cfea0c7338f0fd6bc122f14b6f5524f61480e11df1b389"
        }
      ],
      "licenseConcluded": "NOASSERTION",
      "copyrightText": "NOASSERTION"
    },
    {
      "fileName": "./vcpkg.json",
      "SPDXID": "SPDXRef-port-file-5",
      "checksums": [
        {
          "algorithm": "SHA256",
          "checksumValue": "950a262923b257818acd1e94dc93aabaaf368ee4f99790b31db27fac2aa4529d"
        }
      ],
      "licenseConcluded": "NOASSERTION",
      "copyrightText": "NOASSERTION"
    },
    {
      "fileName": "./lib/pkgconfig/glew.pc",
      "SPDXID": "SPDXRef-binary-file-0",
      "checksums": [
        {
          "algorithm": "SHA256",
          "checksumValue": "5d2e9f67989ef7e9495df14c38a8e807c9f10c6ce54dbb762afc6eb19350f20b"
        }
      ],
      "licenseConcluded": "NOASSERTION",
      "copyrightText": "NOASSERTION"
    },
    {
      "fileName": "./lib/libGLEW.a",
      "SPDXID": "SPDXRef-binary-file-1",
      "checksums": [
        {
          "algorithm": "SHA256",
          "checksumValue": "597b3d6d79a5c6b07f00bc0dc01bb811cde875b8027088678919ae7598088898"
        }
      ],
      "licenseConcluded": "NOASSERTION",
      "copyrightText": "NOASSERTION"
    },
    {
      "fileName": "./include/GL/eglew.h",
      "SPDXID": "SPDXRef-binary-file-2",
      "checksums": [
        {
          "algorithm": "SHA256",
          "checksumValue": "0977b15b9a0e3bc065a2e045a911409b44c4733f23e4c6583c9d54c478de8370"
        }
      ],
      "licenseConcluded": "NOASSERTION",
      "copyrightText": "NOASSERTION"
    },
    {
      "fileName": "./include/GL/wglew.h",
      "SPDXID": "SPDXRef-binary-file-3",
      "checksums": [
        {
          "algorithm": "SHA256",
          "checksumValue": "3d82c47f492d1f0d6153b2f5e3964e2906a7cc439cc28447c032ff99fb871fbd"
        }
      ],
      "licenseConcluded": "NOASSERTION",
      "copyrightText": "NOASSERTION"
    },
    {
      "fileName": "./include/GL/glxew.h",
      "SPDXID": "SPDXRef-binary-file-4",
      "checksums": [
        {
          "algorithm": "SHA256",
          "checksumValue": "0bb9b999b601db3ee3e67ef75fdaa1a377aa09096bdc3ad6efe9398da23b96ca"
        }
      ],
      "licenseConcluded": "NOASSERTION",
      "copyrightText": "NOASSERTION"
    },
    {
      "fileName": "./include/GL/glew.h",
      "SPDXID": "SPDXRef-binary-file-5",
      "checksums": [
        {
          "algorithm": "SHA256",
          "checksumValue": "2dc62c79289d80c2ccca2997aa8fde3a966056811e0df5cce106950d107d4c80"
        }
      ],
      "licenseConcluded": "NOASSERTION",
      "copyrightText": "NOASSERTION"
    },
    {
      "fileName": "./debug/lib/pkgconfig/glew.pc",
      "SPDXID": "SPDXRef-binary-file-6",
      "checksums": [
        {
          "algorithm": "SHA256",
          "checksumValue": "f7095cf3d3c6c51b67f5f0b173be5cda77a0ac240be2b19bdcceff08d58adb90"
        }
      ],
      "licenseConcluded": "NOASSERTION",
      "copyrightText": "NOASSERTION"
    },
    {
      "fileName": "./debug/lib/libGLEWd.a",
      "SPDXID": "SPDXRef-binary-file-7",
      "checksums": [
        {
          "algorithm": "SHA256",
          "checksumValue": "dd944b18058fb01c47fa7e2d81f8916d664fc7706bcebfcb13576e38f171df78"
        }
      ],
      "licenseConcluded": "NOASSERTION",
      "copyrightText": "NOASSERTION"
    },
    {
      "fileName": "./share/glew/copyright",
      "SPDXID": "SPDXRef-binary-file-8",
      "checksums": [
        {
          "algorithm": "SHA256",
          "checksumValue": "8991cd11befec7c6a63662700f03c0cc42e864b6e77c7e70b80297c951a7f0ff"
        }
      ],
      "licenseConcluded": "NOASSERTION",
      "copyrightText": "NOASSERTION"
    },
    {
      "fileName": "./share/glew/glew-targets-release.cmake",
      "SPDXID": "SPDXRef-binary-file-9",
      "checksums": [
        {
          "algorithm": "SHA256",
          "checksumValue": "4458a0c255fb889bfd2ae0d8ef86846cd2e73edbd675835d71bb6d5e55f902be"
        }
      ],
      "licenseConcluded": "NOASSERTION",
      "copyrightText": "NOASSERTION"
    },
    {
      "fileName": "./share/glew/CopyImportedTargetProperties.cmake",
      "SPDXID": "SPDXRef-binary-file-10",
      "checksums": [
        {
          "algorithm": "SHA256",
          "checksumValue": "b7c651036918a5c5bbbc94f9b144f534fc24d7bb4b9f00f02d2440da5f733c44"
        }
      ],
      "licenseConcluded": "NOASSERTION",
      "copyrightText": "NOASSERTION"
    },
    {
      "fileName": "./share/glew/glew-targets.cmake",
      "SPDXID": "SPDXRef-binary-file-11",
      "checksums": [
        {
          "algorithm": "SHA256",
          "checksumValue": "a4843e27d47a30287aeb391bbaf1833542c4422ca3e0ccbd69b4b19261ac313e"
        }
      ],
      "licenseConcluded": "NOASSERTION",
      "copyrightText": "NOASSERTION"
    },
    {
      "fileName": "./share/glew/glew-targets-debug.cmake",
      "SPDXID": "SPDXRef-binary-file-12",
      "checksums": [
        {
          "algorithm": "SHA256",
          "checksumValue": "1341a33b063d6074c61c88bacc4da1ca45b180fdef85a7e59ec970d656843440"
        }
      ],
      "licenseConcluded": "NOASSERTION",
      "copyrightText": "NOASSERTION"
    },
    {
      "fileName": "./share/glew/glew-config.cmake",
      "SPDXID": "SPDXRef-binary-file-13",
      "checksums": [
        {
          "algorithm": "SHA256",
          "checksumValue": "fcd20fed62c08d0634200fa9214c389951d9dfdf2648625b1842c9800e5a8e23"
        }
      ],
      "licenseConcluded": "NOASSERTION",
      "copyrightText": "NOASSERTION"
    },
    {
      "fileName": "./share/glew/vcpkg-cmake-wrapper.cmake",
      "SPDXID": "SPDXRef-binary-file-14",
      "checksums": [
        {
          "algorithm": "SHA256",
          "checksumValue": "8a5f7ae6b0f3ddac45595a1edeb4f3c0d1a612280eaf2d029904e99b6c03816c"
        }
      ],
      "licenseConcluded": "NOASSERTION",
      "copyrightText": "NOASSERTION"
    },
    {
      "fileName": "./share/glew/usage",
      "SPDXID": "SPDXRef-binary-file-15",
      "checksums": [
        {
          "algorithm": "SHA256",
          "checksumValue": "32953fbc39053f27a0cfea0c7338f0fd6bc122f14b6f5524f61480e11df1b389"
        }
      ],
      "licenseConcluded": "NOASSERTION",
      "copyrightText": "NOASSERTION"
    },
    {
      "fileName": "./BUILD_INFO",
      "SPDXID": "SPDXRef-binary-file-16",
      "checksums": [
        {
          "algorithm": "SHA256",
          "checksumValue": "b17d8abcb0fd6454b3c1ec6556988d624863978121b87c51af8b1b6d937db69a"
        }
      ],
      "licenseConcluded": "NOASSERTION",
      "copyrightText": "NOASSERTION"
    }
  ]
}
